loam_iiif/__init__.py
loam_iiif/cache.py
loam_iiif/cli.py
loam_iiif/iiif.py
loam_iiif/py.typed
loam_iiif-0.1.5.dist-info/METADATA
loam_iiif-0.1.5.dist-info/WHEEL
loam_iiif-0.1.5.dist-info/entry_points.txt
loam_iiif-0.1.5.dist-info/licenses/LICENSE
loam_iiif-0.1.5.dist-info/RECORD
