Metadata-Version: 2.4
Name: loam-iiif
Version: 0.1.5
Summary: A command-line tool for fetching IIIF Collections on the Web.
Project-URL: Homepage, https://github.com/nulib-labs/loam-iiif
Project-URL: Repository, https://github.com/nulib-labs/loam-iiif.git
Project-URL: Issues, https://github.com/nulib-labs/loam-iiif/issues
Author-email: Brendan Quinn <brendan-quinn@northwestern.edu>
License-File: LICENSE
Requires-Python: >=3.10
Requires-Dist: click>=8.1.8
Requires-Dist: iiif-prezi3>=2.0.0
Requires-Dist: piffle>=0.6.1
Requires-Dist: requests>=2.32.3
Requires-Dist: rich>=13.9.4
